rand_number__gen/__init__.py
rand_number_gen-0.1.dist-info/LICENSE.txt
rand_number_gen-0.1.dist-info/METADATA
rand_number_gen-0.1.dist-info/WHEEL
rand_number_gen-0.1.dist-info/top_level.txt
rand_number_gen-0.1.dist-info/RECORD
