Metadata-Version: 2.1
Name: rand-number-gen
Version: 0.1
Summary: Random Number Generator
Home-page: https://github.com/maneeshammm/
Author: Maneesha Majeed
Author-email: maneesha_majeed@hotmail.com
License: UNKNOWN
Platform: UNKNOWN
Classifier: Programming Language :: Python :: 3
Classifier: License :: OSI Approved :: MIT License
Classifier: Operating System :: OS Independent
